yawinpty_extra/__init__.py
yawinpty_extra-0.1.0.dev1.dist-info/DESCRIPTION.rst
yawinpty_extra-0.1.0.dev1.dist-info/METADATA
yawinpty_extra-0.1.0.dev1.dist-info/RECORD
yawinpty_extra-0.1.0.dev1.dist-info/WHEEL
yawinpty_extra-0.1.0.dev1.dist-info/metadata.json
yawinpty_extra-0.1.0.dev1.dist-info/top_level.txt
